korcen/__init__.py
korcen/belittle.py
korcen/check.py
korcen/chinese.py
korcen/english.py
korcen/general.py
korcen/japanese.py
korcen/korcen.py
korcen/minor.py
korcen/parent.py
korcen/politics.py
korcen/race.py
korcen/sexual.py
korcen/special.py
korcen-1.0.2.dist-info/METADATA
korcen-1.0.2.dist-info/WHEEL
korcen-1.0.2.dist-info/top_level.txt
korcen-1.0.2.dist-info/RECORD
