Metadata-Version: 2.1
Name: korcen
Version: 1.0.2
Summary: 한국어 비속어 검열
Home-page: https://github.com/KR-korcen/korcen
Author: Tanat
Author-email: shrbwjd05@naver.com
Classifier: Programming Language :: Python :: 3
Classifier: License :: OSI Approved :: MIT License
Classifier: Operating System :: OS Independent
Requires-Python: >=3.6
Requires-Dist: better-profanity
Requires-Dist: OrderedDict
